setup.cfg
setup.py
reacto/__init__.py
reacto/main.py
reacto/start_component.py
reacto.egg-info/PKG-INFO
reacto.egg-info/SOURCES.txt
reacto.egg-info/dependency_links.txt
reacto.egg-info/entry_points.txt
reacto.egg-info/requires.txt
reacto.egg-info/top_level.txt