Metadata-Version: 1.0
Name: reacto
Version: 0.1.1
Summary: Set of commands to maintain react apps and components
Home-page: https://github.com/gvidon/reacto
Author: Artem Rudenko
Author-email: gvidon@ottofeller.com
License: UNKNOWN
Keywords: react,js,tools
Platform: UNKNOWN
